pycomposefile/__init__.py
pycomposefile/compose_file.py
pycomposefile/compose_element/__init__.py
pycomposefile/compose_element/compose_datatype_transformer.py
pycomposefile/compose_element/compose_element.py
pycomposefile/compose_element/compose_list_or_map.py
pycomposefile/compose_element/compose_string_or_list.py
pycomposefile/secrets/__init__.py
pycomposefile/service/__init__.py
pycomposefile/service/service.py
pycomposefile/service/service_blkio_config.py
pycomposefile/service/service_build.py
pycomposefile/service/service_cap.py
pycomposefile/service/service_command.py
pycomposefile/service/service_configs.py
pycomposefile/service/service_credential_spec.py
pycomposefile/service/service_deploy.py
pycomposefile/service/service_environment.py
pycomposefile/service/service_healthcheck.py
pycomposefile/service/service_logging.py
pycomposefile/service/service_misc.py
pycomposefile/service/service_networks.py
pycomposefile/service/service_ports.py
pycomposefile/service/service_volumes.py
pycomposefile-0.0.33.dist-info/WHEEL
pycomposefile-0.0.33.dist-info/METADATA
pycomposefile-0.0.33.dist-info/RECORD
