Metadata-Version: 2.4
Name: pycomposefile
Version: 0.0.33
Summary: Structured deserialization of Docker Compose files.
Keywords: docker,compose
Author-email: Steven Murawski <steven.murawski@microsoft.com>
Requires-Python: >=3.6
License-Expression: MIT
Requires-Dist: pyyaml
Project-URL: Homepage, https://github.com/smurawski/pycomposefile
